{
  "recentFiles": [
    {
      "basename": "PH125 Introduction to Data Science",
      "path": "Sources/PH125 Introduction to Data Science.md"
    },
    {
      "basename": "The big differences between efforts and projects",
      "path": "+ Encounters/The big differences between efforts and projects.md"
    },
    {
      "basename": "Home",
      "path": "Home.md"
    },
    {
      "basename": "Technology",
      "path": "Atlas/Technology.md"
    },
    {
      "basename": "R",
      "path": "Atlas/R.md"
    },
    {
      "basename": "Data Science",
      "path": "Atlas/Data Science.md"
    },
    {
      "basename": "Introduction to Data Science",
      "path": "Sources/Introduction to Data Science.md"
    },
    {
      "basename": "Data Camp Module 3",
      "path": "Sources/Data Camp Module 3.md"
    },
    {
      "basename": "Studies",
      "path": "Atlas/Studies.md"
    },
    {
      "basename": "Untitled",
      "path": "Atlas/Untitled.md"
    },
    {
      "basename": "How ideas and efforts play nicely together",
      "path": "+ Encounters/How ideas and efforts play nicely together.md"
    },
    {
      "basename": "NOMA Method Prompts",
      "path": "Sources/NOMA Method Prompts.md"
    },
    {
      "basename": "PKM",
      "path": "Atlas/PKM.md"
    },
    {
      "basename": "Obsidian Zettelkasten Youtube video Kirsanov",
      "path": "Sources/Obsidian Zettelkasten Youtube video Kirsanov.md"
    },
    {
      "basename": "Zettelkasten",
      "path": "Atlas/Zettelkasten.md"
    },
    {
      "basename": "Obsidian Zettelkasten Note Taking",
      "path": "Sources/Obsidian Zettelkasten Note Taking.md"
    },
    {
      "basename": "Obsidian",
      "path": "Atlas/Obsidian.md"
    },
    {
      "basename": "Obsidian Templater",
      "path": "Sources/Obsidian Templater.md"
    },
    {
      "basename": "Obsidian Callouts",
      "path": "Sources/Obsidian Callouts.md"
    },
    {
      "basename": "Syncing Obsidian and Kindle",
      "path": "Sources/Syncing Obsidian and Kindle.md"
    },
    {
      "basename": "Mastering the Fundamentals of Statistics for Data Science -Basic to Advance Level- Part 1",
      "path": "Sources/Mastering the Fundamentals of Statistics for Data Science -Basic to Advance Level- Part 1.md"
    },
    {
      "basename": "Latex Tutorial Video",
      "path": "Sources/Latex Tutorial Video.md"
    },
    {
      "basename": "Idea Compass",
      "path": "Sources/Idea Compass.md"
    },
    {
      "basename": "Date String Formats",
      "path": "Sources/Date String Formats.md"
    },
    {
      "basename": "Latex",
      "path": "Atlas/Latex.md"
    },
    {
      "basename": "The LYT Workshop",
      "path": "Sources/The LYT Workshop.md"
    },
    {
      "basename": "Complexity (defn)",
      "path": "Cards/Complexity (defn).md"
    },
    {
      "basename": "Commonplace Book",
      "path": "Archive/Cards/Commonplace Book.md"
    },
    {
      "basename": "Cobwebs into Cables",
      "path": "Archive/Cards/Cobwebs into Cables.md"
    },
    {
      "basename": "Chunking",
      "path": "Archive/Cards/Chunking.md"
    },
    {
      "basename": "Changing a habit is really about replacing a routine",
      "path": "Archive/Cards/Changing a habit is really about replacing a routine.md"
    },
    {
      "basename": "Carl Sagan (kit)",
      "path": "Archive/Cards/Carl Sagan (kit).md"
    },
    {
      "basename": "Bottom-up thinking",
      "path": "Archive/Cards/Bottom-up thinking.md"
    },
    {
      "basename": "Bob Bain on Reading Comprehension",
      "path": "Archive/Cards/Bob Bain on Reading Comprehension.md"
    },
    {
      "basename": "BOAT notes",
      "path": "Cards/BOAT notes.md"
    },
    {
      "basename": "Benefits of LYT frameworks",
      "path": "Archive/Cards/Benefits of LYT frameworks.md"
    },
    {
      "basename": "Beginners Guide to Dataview",
      "path": "Cards/Beginners Guide to Dataview.md"
    },
    {
      "basename": "Balancing Challenge and Skill",
      "path": "Archive/Cards/Balancing Challenge and Skill.md"
    },
    {
      "basename": "Attention (re Flow)",
      "path": "Archive/Cards/Attention (re Flow).md"
    },
    {
      "basename": "Assembling a random article on habits",
      "path": "Archive/Cards/Assembling a random article on habits.md"
    },
    {
      "basename": "Art of Link Curation",
      "path": "Cards/Art of Link Curation.md"
    },
    {
      "basename": "Antifragility",
      "path": "Archive/Cards/Antifragility.md"
    },
    {
      "basename": "An asymptotic curve models the development of skills, strength, habits, and more",
      "path": "Cards/An asymptotic curve models the development of skills, strength, habits, and more.md"
    },
    {
      "basename": "2023-03-26",
      "path": "Calendar/2023-03-26.md"
    },
    {
      "basename": "Philosophy MOC (kit)",
      "path": "Atlas/Philosophy MOC (kit).md"
    },
    {
      "basename": "Places MOC",
      "path": "Atlas/Places MOC.md"
    },
    {
      "basename": "People MOC",
      "path": "Atlas/People MOC.md"
    },
    {
      "basename": "2023-03-27",
      "path": "Calendar/2023-03-27.md"
    },
    {
      "basename": "2023-03-28",
      "path": "Calendar/2023-03-28.md"
    }
  ],
  "omittedPaths": [],
  "maxLength": null
}